genova/__init__.py
genova-1.1.4.dist-info/METADATA
genova-1.1.4.dist-info/WHEEL
genova-1.1.4.dist-info/top_level.txt
genova-1.1.4.dist-info/RECORD
