Metadata-Version: 2.1
Name: genova
Version: 1.1.4
Summary: Genova is a versatile Python library that offers a collection of powerful tools for various domains including mathematics, artificial intelligence, finance, and more.
Author: Ege Güvener
